lavarand/__init__.py
lavarand/__version__.py
lavarand/api.py
lavarand/test.py
lavarand-1.1.1.5.dist-info/METADATA
lavarand-1.1.1.5.dist-info/RECORD
lavarand-1.1.1.5.dist-info/WHEEL
lavarand-1.1.1.5.dist-info/top_level.txt
