Metadata-Version: 2.1
Name: lavarand
Version: 1.1.1.5
Summary: Randomness 101: LavaRand in Production
Home-page: https://csprng.xyz/
Author: Maina Nick
Author-email: contact@nickmaina.com
License: DO WHAT THE FUCK YOU WANT TO PUBLIC LICENSE 2.0
Platform: UNKNOWN
Classifier: Development Status :: 5 - Production/Stable
Classifier: Intended Audience :: Developers
Classifier: Natural Language :: English
Classifier: Programming Language :: Python
Classifier: Programming Language :: Python :: 2.6
Classifier: Programming Language :: Python :: 2.7
Classifier: Programming Language :: Python :: 3
Classifier: Programming Language :: Python :: 3.3
Classifier: Programming Language :: Python :: 3.4
Classifier: Programming Language :: Python :: 3.5
Classifier: Programming Language :: Python :: 3.6
Classifier: Programming Language :: Python :: Implementation :: CPython
Classifier: Programming Language :: Python :: Implementation :: PyPy
Requires-Dist: requests
